thiruklib1/__init__.py
thiruklib1/greet.py
thiruklib1-0.0.1.dist-info/METADATA
thiruklib1-0.0.1.dist-info/WHEEL
thiruklib1-0.0.1.dist-info/top_level.txt
thiruklib1-0.0.1.dist-info/RECORD
