Metadata-Version: 2.4
Name: thiruklib1
Version: 0.0.1
Summary: this is the package for greeting
Home-page: https://github.com/thiruk/thiruklib1
Author: thiru
Author-email: thirukguru@gmail.com
Classifier: Programming Language :: Python :: 3
Classifier: License :: OSI Approved :: MIT License
Classifier: Operating System :: OS Independent
Requires-Python: >=3.6
Dynamic: author
Dynamic: author-email
Dynamic: classifier
Dynamic: description
Dynamic: description-content-type
Dynamic: home-page
Dynamic: requires-python
Dynamic: summary
